monadiacpy/__init__.py
monadiacpy/maybe.py
monadiacpy/requests.py
monadiacpy/result_or_failure.py
monadiacpy-0.1.0.dist-info/WHEEL
monadiacpy-0.1.0.dist-info/METADATA
monadiacpy-0.1.0.dist-info/RECORD
