Metadata-Version: 2.1
Name: monadiacpy
Version: 0.1.0
Summary: 
Author: CaMMelo
Author-email: cmelo.marcelo.pereira@gmail.com
Requires-Python: >=3.10,<4.0
Classifier: Programming Language :: Python :: 3
Classifier: Programming Language :: Python :: 3.10
Requires-Dist: requests (>=2.28.1,<3.0.0)
